{
  "airports": {
    "CDG": {"name": "Charles de Gaulle", "city": "Paris", "country": "FR"},
    "ORY": {"name": "Orly", "city": "Paris", "country": "FR"},
    "LHR": {"name": "Heathrow", "city": "London", "country": "GB"},
    "LGW": {"name": "Gatwick", "city": "London", "country": "GB"},
    "AMS": {"name": "Schiphol", "city": "Amsterdam", "country": "NL"},
    "FRA": {"name": "Frankfurt", "city": "Frankfurt", "country": "DE"},
    "MAD": {"name": "Barajas", "city": "Madrid", "country": "ES"},
    "BCN": {"name": "El Prat", "city": "Barcelona", "country": "ES"},
    "FCO": {"name": "Fiumicino", "city": "Rome", "country": "IT"},
    "MXP": {"name": "Malpensa", "city": "Milan", "country": "IT"},
    "ZRH": {"name": "Zurich", "city": "Zurich", "country": "CH"},
    "VIE": {"name": "Vienna", "city": "Vienna", "country": "AT"},
    "BRU": {"name": "Brussels", "city": "Brussels", "country": "BE"},
    "CPH": {"name": "Copenhagen", "city": "Copenhagen", "country": "DK"},
    "ARN": {"name": "Arlanda", "city": "Stockholm", "country": "SE"},
    "OSL": {"name": "Gardermoen", "city": "Oslo", "country": "NO"},
    "HEL": {"name": "Helsinki", "city": "Helsinki", "country": "FI"},
    "DUB": {"name": "Dublin", "city": "Dublin", "country": "IE"},
    "LIS": {"name": "Lisbon", "city": "Lisbon", "country": "PT"},
    "ATH": {"name": "Eleftherios Venizelos", "city": "Athens", "country": "GR"},
    "JFK": {"name": "John F. Kennedy", "city": "New York", "country": "US"},
    "EWR": {"name": "Newark", "city": "New York", "country": "US"},
    "LAX": {"name": "Los Angeles Intl", "city": "Los Angeles", "country": "US"},
    "ORD": {"name": "O'Hare", "city": "Chicago", "country": "US"},
    "MIA": {"name": "Miami Intl", "city": "Miami", "country": "US"},
    "SFO": {"name": "San Francisco Intl", "city": "San Francisco", "country": "US"},
    "BOS": {"name": "Logan", "city": "Boston", "country": "US"},
    "DFW": {"name": "Dallas Fort Worth", "city": "Dallas", "country": "US"},
    "ATL": {"name": "Hartsfield-Jackson", "city": "Atlanta", "country": "US"},
    "SEA": {"name": "Sea-Tac", "city": "Seattle", "country": "US"},
    "YUL": {"name": "Trudeau", "city": "Montreal", "country": "CA"},
    "YYZ": {"name": "Pearson", "city": "Toronto", "country": "CA"},
    "YVR": {"name": "Vancouver Intl", "city": "Vancouver", "country": "CA"},
    "DXB": {"name": "Dubai Intl", "city": "Dubai", "country": "AE"},
    "AUH": {"name": "Abu Dhabi Intl", "city": "Abu Dhabi", "country": "AE"},
    "DOH": {"name": "Hamad Intl", "city": "Doha", "country": "QA"},
    "SIN": {"name": "Changi", "city": "Singapore", "country": "SG"},
    "HKG": {"name": "Chek Lap Kok", "city": "Hong Kong", "country": "HK"},
    "NRT": {"name": "Narita", "city": "Tokyo", "country": "JP"},
    "HND": {"name": "Haneda", "city": "Tokyo", "country": "JP"},
    "ICN": {"name": "Incheon", "city": "Seoul", "country": "KR"},
    "PVG": {"name": "Pudong", "city": "Shanghai", "country": "CN"},
    "PEK": {"name": "Capital", "city": "Beijing", "country": "CN"},
    "SYD": {"name": "Kingsford Smith", "city": "Sydney", "country": "AU"},
    "MEL": {"name": "Melbourne", "city": "Melbourne", "country": "AU"},
    "GRU": {"name": "Guarulhos", "city": "São Paulo", "country": "BR"},
    "EZE": {"name": "Ministro Pistarini", "city": "Buenos Aires", "country": "AR"},
    "BOG": {"name": "El Dorado", "city": "Bogotá", "country": "CO"},
    "CAI": {"name": "Cairo Intl", "city": "Cairo", "country": "EG"},
    "JNB": {"name": "O.R. Tambo", "city": "Johannesburg", "country": "ZA"},
    "PKX": {"name": "Daxing Intl", "city": "Beijing", "country": "CN"},
    "CAN": {"name": "Baiyun Intl", "city": "Guangzhou", "country": "CN"},
    "CTU": {"name": "Tianfu Intl", "city": "Chengdu", "country": "CN"},
    "XIY": {"name": "Xianyang Intl", "city": "Xi'an", "country": "CN"},
    "DEL": {"name": "Indira Gandhi Intl", "city": "Delhi", "country": "IN"},
    "BOM": {"name": "Chhatrapati Shivaji Maharaj Intl", "city": "Mumbai", "country": "IN"},
    "BLR": {"name": "Kempegowda Intl", "city": "Bangalore", "country": "IN"},
    "MAA": {"name": "Chennai Intl", "city": "Chennai", "country": "IN"},
    "HYD": {"name": "Rajiv Gandhi Intl", "city": "Hyderabad", "country": "IN"},
    "CCU": {"name": "Netaji Subhas Chandra Bose Intl", "city": "Kolkata", "country": "IN"},
    "IST": {"name": "Istanbul Airport", "city": "Istanbul", "country": "TR"},
    "SAW": {"name": "Sabiha Gökçen Intl", "city": "Istanbul", "country": "TR"},
    "TLV": {"name": "Ben Gurion Intl", "city": "Tel Aviv", "country": "IL"},
    "AMM": {"name": "Queen Alia Intl", "city": "Amman", "country": "JO"},
    "KWI": {"name": "Kuwait Intl", "city": "Kuwait City", "country": "KW"},
    "BAH": {"name": "Bahrain Intl", "city": "Manama", "country": "BH"},
    "MCT": {"name": "Muscat Intl", "city": "Muscat", "country": "OM"},
    "RUH": {"name": "King Khalid Intl", "city": "Riyadh", "country": "SA"},
    "JED": {"name": "King Abdulaziz Intl", "city": "Jeddah", "country": "SA"},
    "BKK": {"name": "Suvarnabhumi", "city": "Bangkok", "country": "TH"},
    "DMK": {"name": "Don Mueang Intl", "city": "Bangkok", "country": "TH"},
    "KUL": {"name": "Kuala Lumpur Intl", "city": "Kuala Lumpur", "country": "MY"},
    "CGK": {"name": "Soekarno-Hatta Intl", "city": "Jakarta", "country": "ID"},
    "DPS": {"name": "Ngurah Rai Intl", "city": "Bali", "country": "ID"},
    "SGN": {"name": "Tan Son Nhat Intl", "city": "Ho Chi Minh City", "country": "VN"},
    "HAN": {"name": "Noi Bai Intl", "city": "Hanoi", "country": "VN"},
    "MNL": {"name": "Ninoy Aquino Intl", "city": "Manila", "country": "PH"},
    "CEB": {"name": "Mactan-Cebu Intl", "city": "Cebu", "country": "PH"},
    "RGN": {"name": "Yangon Intl", "city": "Yangon", "country": "MM"},
    "PNH": {"name": "Phnom Penh Intl", "city": "Phnom Penh", "country": "KH"},
    "VTE": {"name": "Wattay Intl", "city": "Vientiane", "country": "LA"},
    "CMB": {"name": "Bandaranaike Intl", "city": "Colombo", "country": "LK"},
    "DAC": {"name": "Hazrat Shahjalal Intl", "city": "Dhaka", "country": "BD"},
    "KTM": {"name": "Tribhuvan Intl", "city": "Kathmandu", "country": "NP"},
    "KHI": {"name": "Jinnah Intl", "city": "Karachi", "country": "PK"},
    "LHE": {"name": "Allama Iqbal Intl", "city": "Lahore", "country": "PK"},
    "ISB": {"name": "Islamabad Intl", "city": "Islamabad", "country": "PK"},
    "AKL": {"name": "Auckland Intl", "city": "Auckland", "country": "NZ"},
    "CHC": {"name": "Christchurch Intl", "city": "Christchurch", "country": "NZ"},
    "PER": {"name": "Perth Airport", "city": "Perth", "country": "AU"},
    "BNE": {"name": "Brisbane Airport", "city": "Brisbane", "country": "AU"},
    "NBO": {"name": "Jomo Kenyatta Intl", "city": "Nairobi", "country": "KE"},
    "MBA": {"name": "Moi Intl", "city": "Mombasa", "country": "KE"},
    "ADD": {"name": "Bole Intl", "city": "Addis Ababa", "country": "ET"},
    "LOS": {"name": "Murtala Muhammed Intl", "city": "Lagos", "country": "NG"},
    "ABV": {"name": "Nnamdi Azikiwe Intl", "city": "Abuja", "country": "NG"},
    "ACC": {"name": "Kotoka Intl", "city": "Accra", "country": "GH"},
    "CMN": {"name": "Mohammed V Intl", "city": "Casablanca", "country": "MA"},
    "RAK": {"name": "Marrakech Menara", "city": "Marrakech", "country": "MA"},
    "TUN": {"name": "Tunis-Carthage Intl", "city": "Tunis", "country": "TN"},
    "ALG": {"name": "Houari Boumediene", "city": "Algiers", "country": "DZ"},
    "TIP": {"name": "Mitiga Intl", "city": "Tripoli", "country": "LY"},
    "CPT": {"name": "Cape Town Intl", "city": "Cape Town", "country": "ZA"},
    "DUR": {"name": "King Shaka Intl", "city": "Durban", "country": "ZA"},
    "EBB": {"name": "Entebbe Intl", "city": "Kampala", "country": "UG"},
    "KGL": {"name": "Kigali Intl", "city": "Kigali", "country": "RW"},
    "DAR": {"name": "Julius Nyerere Intl", "city": "Dar es Salaam", "country": "TZ"},
    "ZNZ": {"name": "Abeid Amani Karume Intl", "city": "Zanzibar", "country": "TZ"},
    "ABJ": {"name": "Félix-Houphouët-Boigny Intl", "city": "Abidjan", "country": "CI"},
    "DKR": {"name": "Blaise Diagne Intl", "city": "Dakar", "country": "SN"},
    "OUA": {"name": "Ouagadougou Intl", "city": "Ouagadougou", "country": "BF"},
    "BKO": {"name": "Bamako-Sénou Intl", "city": "Bamako", "country": "ML"},
    "NDJ": {"name": "Hassan Djamous Intl", "city": "N'Djamena", "country": "TD"},
    "FIH": {"name": "N'Djili Intl", "city": "Kinshasa", "country": "CD"},
    "LAD": {"name": "Quatro de Fevereiro Intl", "city": "Luanda", "country": "AO"},
    "LBV": {"name": "Léon-Mba Intl", "city": "Libreville", "country": "GA"},
    "LUN": {"name": "Kenneth Kaunda Intl", "city": "Lusaka", "country": "ZM"},
    "HRE": {"name": "Robert Gabriel Mugabe Intl", "city": "Harare", "country": "ZW"},
    "MPM": {"name": "Maputo Intl", "city": "Maputo", "country": "MZ"},
    "WDH": {"name": "Hosea Kutako Intl", "city": "Windhoek", "country": "NA"},
    "GBE": {"name": "Sir Seretse Khama Intl", "city": "Gaborone", "country": "BW"},
    "MRU": {"name": "Sir Seewoosagur Ramgoolam Intl", "city": "Port Louis", "country": "MU"},
    "SEZ": {"name": "Seychelles Intl", "city": "Victoria", "country": "SC"},
    "TNR": {"name": "Ivato Intl", "city": "Antananarivo", "country": "MG"},
    "ASM": {"name": "Asmara Intl", "city": "Asmara", "country": "ER"},
    "KRT": {"name": "Khartoum Intl", "city": "Khartoum", "country": "SD"},
    "FNA": {"name": "Lungi Intl", "city": "Freetown", "country": "SL"},
    "BJL": {"name": "Banjul Intl", "city": "Banjul", "country": "GM"},
    "GIG": {"name": "Galeão Intl", "city": "Rio de Janeiro", "country": "BR"},
    "SDU": {"name": "Santos Dumont", "city": "Rio de Janeiro", "country": "BR"},
    "BSB": {"name": "Juscelino Kubitschek Intl", "city": "Brasília", "country": "BR"},
    "SSA": {"name": "Luís Eduardo Magalhães Intl", "city": "Salvador", "country": "BR"},
    "REC": {"name": "Recife Intl", "city": "Recife", "country": "BR"},
    "FOR": {"name": "Pinto Martins Intl", "city": "Fortaleza", "country": "BR"},
    "POA": {"name": "Salgado Filho Intl", "city": "Porto Alegre", "country": "BR"},
    "SCL": {"name": "Comodoro Arturo Merino Benítez Intl", "city": "Santiago", "country": "CL"},
    "LIM": {"name": "Jorge Chávez Intl", "city": "Lima", "country": "PE"},
    "CUZ": {"name": "Alejandro Velasco Astete Intl", "city": "Cusco", "country": "PE"},
    "UIO": {"name": "Mariscal Sucre Intl", "city": "Quito", "country": "EC"},
    "GYE": {"name": "José Joaquín de Olmedo Intl", "city": "Guayaquil", "country": "EC"},
    "MVD": {"name": "Carrasco Intl", "city": "Montevideo", "country": "UY"},
    "ASU": {"name": "Silvio Pettirossi Intl", "city": "Asunción", "country": "PY"},
    "VVI": {"name": "Viru Viru Intl", "city": "Santa Cruz", "country": "BO"},
    "LPB": {"name": "El Alto Intl", "city": "La Paz", "country": "BO"},
    "CCS": {"name": "Simón Bolívar Intl", "city": "Caracas", "country": "VE"},
    "MDE": {"name": "José María Córdova Intl", "city": "Medellín", "country": "CO"},
    "CLO": {"name": "Alfonso Bonilla Aragón Intl", "city": "Cali", "country": "CO"},
    "GYM": {"name": "Mariscal Lamar Intl", "city": "Guayaquil", "country": "EC"},
    "PTY": {"name": "Tocumen Intl", "city": "Panama City", "country": "PA"},
    "GUA": {"name": "La Aurora Intl", "city": "Guatemala City", "country": "GT"},
    "SJO": {"name": "Juan Santamaría Intl", "city": "San José", "country": "CR"},
    "SAL": {"name": "Monseñor Romero Intl", "city": "San Salvador", "country": "SV"},
    "SDQ": {"name": "Las Américas Intl", "city": "Santo Domingo", "country": "DO"},
    "HAV": {"name": "José Martí Intl", "city": "Havana", "country": "CU"},
    "MBJ": {"name": "Sangster Intl", "city": "Montego Bay", "country": "JM"},
    "KIN": {"name": "Norman Manley Intl", "city": "Kingston", "country": "JM"}
  },
  "airlines": {
    "AF": {"name": "Air France", "country": "FR"},
    "BA": {"name": "British Airways", "country": "GB"},
    "LH": {"name": "Lufthansa", "country": "DE"},
    "KL": {"name": "KLM", "country": "NL"},
    "IB": {"name": "Iberia", "country": "ES"},
    "AZ": {"name": "ITA Airways", "country": "IT"},
    "LX": {"name": "Swiss", "country": "CH"},
    "OS": {"name": "Austrian", "country": "AT"},
    "SN": {"name": "Brussels Airlines", "country": "BE"},
    "SK": {"name": "SAS", "country": "SE"},
    "AY": {"name": "Finnair", "country": "FI"},
    "EI": {"name": "Aer Lingus", "country": "IE"},
    "TP": {"name": "TAP Air Portugal", "country": "PT"},
    "AA": {"name": "American Airlines", "country": "US"},
    "UA": {"name": "United Airlines", "country": "US"},
    "DL": {"name": "Delta", "country": "US"},
    "B6": {"name": "JetBlue", "country": "US"},
    "WN": {"name": "Southwest", "country": "US"},
    "AS": {"name": "Alaska Airlines", "country": "US"},
    "AC": {"name": "Air Canada", "country": "CA"},
    "EK": {"name": "Emirates", "country": "AE"},
    "EY": {"name": "Etihad", "country": "AE"},
    "QR": {"name": "Qatar Airways", "country": "QA"},
    "SQ": {"name": "Singapore Airlines", "country": "SG"},
    "CX": {"name": "Cathay Pacific", "country": "HK"},
    "NH": {"name": "ANA", "country": "JP"},
    "JL": {"name": "Japan Airlines", "country": "JP"},
    "OZ": {"name": "Asiana", "country": "KR"},
    "KE": {"name": "Korean Air", "country": "KR"},
    "MU": {"name": "China Eastern", "country": "CN"},
    "CA": {"name": "Air China", "country": "CN"},
    "QF": {"name": "Qantas", "country": "AU"},
    "LA": {"name": "LATAM", "country": "CL"},
    "G3": {"name": "Gol", "country": "BR"},
    "MS": {"name": "EgyptAir", "country": "EG"},
    "ET": {"name": "Ethiopian Airlines", "country": "ET"},
    "FR": {"name": "Ryanair", "country": "IE"},
    "U2": {"name": "EasyJet", "country": "GB"},
    "W6": {"name": "Wizz Air", "country": "HU"},
    "VY": {"name": "Vueling", "country": "ES"}
  }
}
